reflex_mafs/__init__.py
reflex_mafs/mafs.py
reflex_mafs-0.0.1.dist-info/METADATA
reflex_mafs-0.0.1.dist-info/WHEEL
reflex_mafs-0.0.1.dist-info/top_level.txt
reflex_mafs-0.0.1.dist-info/RECORD
